aexpy/__init__.py
aexpy/__main__.py
aexpy/cli.py
aexpy/producers.py
aexpy/services.py
aexpy/utils.py
aexpy/apidetector/__init__.py
aexpy/apidetector/__main__.py
aexpy/apidetector/abcs.py
aexpy/apidetector/compat.py
aexpy/apidetector/ignores.py
aexpy/apidetector/processor.py
aexpy/diffing/__init__.py
aexpy/diffing/default.py
aexpy/diffing/differs/__init__.py
aexpy/diffing/differs/checkers.py
aexpy/diffing/differs/default.py
aexpy/diffing/differs/contraints/__init__.py
aexpy/diffing/differs/contraints/aliases.py
aexpy/diffing/differs/contraints/attributes.py
aexpy/diffing/differs/contraints/classes.py
aexpy/diffing/differs/contraints/externals.py
aexpy/diffing/differs/contraints/functions.py
aexpy/diffing/differs/contraints/modules.py
aexpy/diffing/differs/contraints/parameters.py
aexpy/diffing/differs/contraints/types.py
aexpy/diffing/evaluators/__init__.py
aexpy/diffing/evaluators/checkers.py
aexpy/diffing/evaluators/default.py
aexpy/diffing/evaluators/evals.py
aexpy/diffing/evaluators/typing.py
aexpy/environments/__init__.py
aexpy/environments/conda.py
aexpy/environments/mamba.py
aexpy/extracting/__init__.py
aexpy/extracting/attributes.py
aexpy/extracting/base.py
aexpy/extracting/default.py
aexpy/extracting/environment.py
aexpy/extracting/kwargs.py
aexpy/extracting/types.py
aexpy/extracting/enriching/__init__.py
aexpy/extracting/enriching/attributes.py
aexpy/extracting/enriching/kwargs.py
aexpy/extracting/enriching/types.py
aexpy/extracting/enriching/callgraph/__init__.py
aexpy/extracting/enriching/callgraph/basic.py
aexpy/extracting/enriching/callgraph/type.py
aexpy/extracting/third/__init__.py
aexpy/extracting/third/mypyserver.py
aexpy/extracting/third/mypyvisitor.py
aexpy/io/__init__.py
aexpy/io/gzip.py
aexpy/models/__init__.py
aexpy/models/description.py
aexpy/models/difference.py
aexpy/models/typing.py
aexpy/preprocessing/__init__.py
aexpy/preprocessing/counter.py
aexpy/preprocessing/download.py
aexpy/preprocessing/pypi.py
aexpy/preprocessing/wheel.py
aexpy-0.4.3.dist-info/METADATA
aexpy-0.4.3.dist-info/WHEEL
aexpy-0.4.3.dist-info/entry_points.txt
aexpy-0.4.3.dist-info/licenses/LICENSE
aexpy-0.4.3.dist-info/RECORD
