Metadata-Version: 2.1
Name: aexpy
Version: 0.4.3
Summary: AexPy /eɪkspaɪ/ is Api EXplorer in PYthon for detecting API breaking changes in Python packages.
Project-URL: Homepage, https://aexpy.netlify.app/
Project-URL: Documentation, https://aexpy-docs.netlify.app/
Project-URL: Repository, https://github.com/StardustDL/aexpy
Project-URL: Issues, https://github.com/StardustDL/aexpy/issues
Project-URL: Changelog, https://github.com/StardustDL/aexpy/releases
Author-email: StardustDL <stardustdl@163.com>
License-File: LICENSE
Keywords: API,Backward Compatibility,Breaking Change,Python
Classifier: Intended Audience :: Developers
Classifier: License :: OSI Approved :: Mozilla Public License 2.0 (MPL 2.0)
Classifier: Operating System :: OS Independent
Classifier: Programming Language :: Python :: 3
Classifier: Programming Language :: Python :: 3.12
Classifier: Programming Language :: Python :: Implementation :: CPython
Classifier: Topic :: Software Development :: Quality Assurance
Classifier: Topic :: Utilities
Requires-Python: >=3.12
Requires-Dist: click>=8.0.0
Requires-Dist: mypy>=0.981
Requires-Dist: pydantic>=2.0.2
